mongo_objects/__init__.py
mongo_objects-1.2.6.dist-info/METADATA
mongo_objects-1.2.6.dist-info/WHEEL
mongo_objects-1.2.6.dist-info/licenses/LICENSE.txt
mongo_objects-1.2.6.dist-info/RECORD
