Metadata-Version: 2.3
Name: mongo_objects
Version: 1.2.6
Summary: Access MongoDB documents and subdocuments through user-defined UserDict and proxy objects.
Project-URL: Homepage, https://github.com/lindstrom-j/mongo_objects
Project-URL: Documentation, https://mongo-objects.headwaters.com.sg/en/latest/
Project-URL: Issues, https://github.com/lindstrom-j/mongo_objects/issues
Author-email: Jonathan Lindstrom <lindstrom.j@headwaters.com.sg>
License: MIT License
License-File: LICENSE.txt
Keywords: Mongo,MongoDB,pymongo
Classifier: Development Status :: 5 - Production/Stable
Classifier: License :: OSI Approved :: MIT License
Classifier: Operating System :: OS Independent
Classifier: Programming Language :: Python :: 3
Requires-Python: >=3.8
Requires-Dist: pymongo
